odoo9_addon_base_export_manager-9.0.1.1.0.99.dev19-py2.7-nspkg.pth
odoo9_addon_base_export_manager-9.0.1.1.0.99.dev19.dist-info/DESCRIPTION.rst
odoo9_addon_base_export_manager-9.0.1.1.0.99.dev19.dist-info/METADATA
odoo9_addon_base_export_manager-9.0.1.1.0.99.dev19.dist-info/RECORD
odoo9_addon_base_export_manager-9.0.1.1.0.99.dev19.dist-info/WHEEL
odoo9_addon_base_export_manager-9.0.1.1.0.99.dev19.dist-info/metadata.json
odoo9_addon_base_export_manager-9.0.1.1.0.99.dev19.dist-info/namespace_packages.txt
odoo9_addon_base_export_manager-9.0.1.1.0.99.dev19.dist-info/top_level.txt
odoo_addons/base_export_manager/README.rst
odoo_addons/base_export_manager/__init__.py
odoo_addons/base_export_manager/__openerp__.py
odoo_addons/base_export_manager/data/ir_exports_data.xml
odoo_addons/base_export_manager/i18n/ar.po
odoo_addons/base_export_manager/i18n/base_export_manager.pot
odoo_addons/base_export_manager/i18n/bg.po
odoo_addons/base_export_manager/i18n/bs.po
odoo_addons/base_export_manager/i18n/ca.po
odoo_addons/base_export_manager/i18n/cs.po
odoo_addons/base_export_manager/i18n/da.po
odoo_addons/base_export_manager/i18n/da_DK.po
odoo_addons/base_export_manager/i18n/de.po
odoo_addons/base_export_manager/i18n/el_GR.po
odoo_addons/base_export_manager/i18n/en_GB.po
odoo_addons/base_export_manager/i18n/es.po
odoo_addons/base_export_manager/i18n/es_AR.po
odoo_addons/base_export_manager/i18n/es_CL.po
odoo_addons/base_export_manager/i18n/es_CO.po
odoo_addons/base_export_manager/i18n/es_CR.po
odoo_addons/base_export_manager/i18n/es_DO.po
odoo_addons/base_export_manager/i18n/es_EC.po
odoo_addons/base_export_manager/i18n/es_ES.po
odoo_addons/base_export_manager/i18n/es_MX.po
odoo_addons/base_export_manager/i18n/es_PE.po
odoo_addons/base_export_manager/i18n/es_PY.po
odoo_addons/base_export_manager/i18n/es_VE.po
odoo_addons/base_export_manager/i18n/et.po
odoo_addons/base_export_manager/i18n/eu.po
odoo_addons/base_export_manager/i18n/fa.po
odoo_addons/base_export_manager/i18n/fi.po
odoo_addons/base_export_manager/i18n/fr.po
odoo_addons/base_export_manager/i18n/fr_CA.po
odoo_addons/base_export_manager/i18n/fr_CH.po
odoo_addons/base_export_manager/i18n/gl.po
odoo_addons/base_export_manager/i18n/he.po
odoo_addons/base_export_manager/i18n/hr.po
odoo_addons/base_export_manager/i18n/hr_HR.po
odoo_addons/base_export_manager/i18n/hu.po
odoo_addons/base_export_manager/i18n/id.po
odoo_addons/base_export_manager/i18n/it.po
