Metadata-Version: 2.0
Name: odoo9-addon-base-export-manager
Version: 9.0.1.1.0.99.dev19
Summary: Manage model export profiles
Home-page: http://www.antiun.com
Author: Antiun Ingeniería S.L., Tecnativa, LasLabs, Ursa Information Systems, Odoo Community Association (OCA)
Author-email: support@odoo-community.org
License: AGPL-3
Platform: UNKNOWN
Classifier: Programming Language :: Python
Classifier: Framework :: Odoo
Classifier: License :: OSI Approved :: GNU Affero General Public License v3
Requires-Python: ~=2.7
Requires-Dist: odoo (<9.1a,>=9.0a)
